{
  "best-products": [
    {
      "id": 1,
      "code": "K-01",
      "nama": "Sate Ayam",
      "harga": 16000,
      "is_ready": true,
      "gambar": "sate-ayam.jpg"
    },
    {
      "id": 2,
      "code": "K-02",
      "nama": "Nasi Goreng Telur",
      "harga": 14000,
      "is_ready": true,
      "gambar": "nasi-goreng-telor.jpg"
    },
    {
      "id": 3,
      "code": "K-03",
      "nama": "Nasi Remes",
      "harga": 12000,
      "is_ready": true,
      "gambar": "nasi-rames.jpg"
    },
    {
      "id": 4,
      "code": "K-04",
      "nama": "Mie Ayam Bakso",
      "harga": 14000,
      "is_ready": true,
      "gambar": "mie-ayam-bakso.jpg"
    }
  ],
  "products": [
    {
      "id": 1,
      "code": "K-01",
      "nama": "Sate Ayam",
      "harga": 16000,
      "is_ready": true,
      "gambar": "sate-ayam.jpg"
    },
    {
      "id": 2,
      "code": "K-02",
      "nama": "Nasi Goreng Telur",
      "harga": 14000,
      "is_ready": true,
      "gambar": "nasi-goreng-telor.jpg"
    },
    {
      "id": 3,
      "code": "K-03",
      "nama": "Nasi Remes",
      "harga": 12000,
      "is_ready": true,
      "gambar": "nasi-rames.jpg"
    },
    {
      "id": 4,
      "code": "K-04",
      "nama": "Mie Ayam Bakso",
      "harga": 14000,
      "is_ready": true,
      "gambar": "mie-ayam-bakso.jpg"
    },
    {
      "id": 5,
      "code": "K-05",
      "nama": "Mie Goreng",
      "harga": 14000,
      "is_ready": true,
      "gambar": "mie-goreng.jpg"
    },
    {
      "id": 6,
      "code": "K-06",
      "nama": "Bakso",
      "harga": 10000,
      "is_ready": true,
      "gambar": "bakso.jpg"
    },
    {
      "id": 7,
      "code": "K-07",
      "nama": "Pangsit 6 pcs",
      "harga": 5000,
      "is_ready": true,
      "gambar": "pangsit.jpg"
    },
    {
      "id": 8,
      "code": "K-08",
      "nama": "Kentang Goreng",
      "harga": 5000,
      "is_ready": true,
      "gambar": "kentang-goreng.jpg"
    },
    {
      "id": 9,
      "code": "K-09",
      "nama": "Lontong Opor Ayam",
      "harga": 5000,
      "is_ready": true,
      "gambar": "lontong-opor-ayam.jpg"
    }
  ],
  "cart": [],
  "orders": []
}